django_saml2_framework/__init__.py
django_saml2_framework/admin.py
django_saml2_framework/apps.py
django_saml2_framework/cache.py
django_saml2_framework/ident.py
django_saml2_framework/models.py
django_saml2_framework/session.py
django_saml2_framework/signals.py
django_saml2_framework/urls.py
django_saml2_framework/utils.py
django_saml2_framework/views.py
django_saml2_framework/attributemaps/__init__.py
django_saml2_framework/attributemaps/basic.py
django_saml2_framework/attributemaps/unspecified.py
django_saml2_framework/attributemaps/uri.py
django_saml2_framework/auth/__init__.py
django_saml2_framework/management/__init__.py
django_saml2_framework/management/commands/__init__.py
django_saml2_framework/management/commands/generate_key.py
django_saml2_framework/migrations/0001_initial.py
django_saml2_framework/migrations/0002_auto_20190124_2235.py
django_saml2_framework/migrations/0003_auto_20190126_1940.py
django_saml2_framework/migrations/0004_auto_20190126_2038.py
django_saml2_framework/migrations/0005_auto_20190126_2212.py
django_saml2_framework/migrations/0006_auto_20190128_1612.py
django_saml2_framework/migrations/0007_auto_20190128_1614.py
django_saml2_framework/migrations/0008_auto_20190204_1715.py
django_saml2_framework/migrations/0009_serviceprovider_create_user.py
django_saml2_framework/migrations/0010_auto_20190205_1425.py
django_saml2_framework/migrations/0011_auto_20190206_1329.py
django_saml2_framework/migrations/0012_auto_20190206_1334.py
django_saml2_framework/migrations/0013_auto_20190206_1451.py
django_saml2_framework/migrations/0014_auto_20190207_1319.py
django_saml2_framework/migrations/0015_auto_20190209_1359.py
django_saml2_framework/migrations/0016_auto_20190209_1456.py
django_saml2_framework/migrations/0017_auto_20190325_1711.py
django_saml2_framework/migrations/__init__.py
django_saml2_framework/tests/__init__.py
django_saml2_framework/tests/utils.py
django_saml2_framework-0.0.0b11.dist-info/METADATA
django_saml2_framework-0.0.0b11.dist-info/WHEEL
django_saml2_framework-0.0.0b11.dist-info/top_level.txt
django_saml2_framework-0.0.0b11.dist-info/RECORD
